setup.py
jester/__init__.py
jester/aws.py
jester/cache.py
jester/clock.py
jester/constants.py
jester/funcs.py
jester/mysql.py
jester/utils.py
jester.egg-info/PKG-INFO
jester.egg-info/SOURCES.txt
jester.egg-info/dependency_links.txt
jester.egg-info/not-zip-safe
jester.egg-info/top_level.txt