Metadata-Version: 1.0
Name: jester
Version: 0.24
Summary: Utilities for web applications in Python3.4
Home-page: http://github.com/CastleAds/jester
Author: Nicholas Connor
Author-email: nick@castleads.com
License: MIT
Platform: UNKNOWN
